ament_black/__init__.py
ament_black/main.py
ament_black-0.14.3.data/data/share/ament_black/package.xml
ament_black-0.14.3.data/data/share/ament_index/resource_index/packages/ament_black
ament_black-0.14.3.dist-info/METADATA
ament_black-0.14.3.dist-info/WHEEL
ament_black-0.14.3.dist-info/entry_points.txt
ament_black-0.14.3.dist-info/top_level.txt
ament_black-0.14.3.dist-info/RECORD
